{
    "state": {
        "boats": [
            {
                "id": "b0",
                "x": 3.0,
                "y": 0.0,
                "index": 0
            },
            {
                "id": "b1",
                "x": 7.0,
                "y": 0.0,
                "index": 1
            }
        ],
        "persons": [
            {
                "id": "p0",
                "d": -370.0,
                "saved": false,
                "index": 0
            }
        ],
        "cost": 0
    },
    "problem": {
        "goal": {
            "saved_persons": [
                "p0"
            ]
        }
    }
}